pushnotifier/PushNotifier.py
pushnotifier/__init__.py
pushnotifier/exceptions.py
tests/__init__.py
tests/conftest.py
tests/test_pushnotifier.py
pushnotifier-1.3.0.dist-info/LICENSE
pushnotifier-1.3.0.dist-info/METADATA
pushnotifier-1.3.0.dist-info/WHEEL
pushnotifier-1.3.0.dist-info/top_level.txt
pushnotifier-1.3.0.dist-info/RECORD
