Metadata-Version: 2.1
Name: pushnotifier
Version: 1.3.0
Summary: A python package for easy interaction with https://pushnotifier.de/
Home-page: https://github.com/tomg404/pushnotifier-python
Author: Tom Gaimann
Author-email: tom.gaimann+pushnotifier@outlook.com
Classifier: Programming Language :: Python :: 3.9
Classifier: Programming Language :: Python :: 3.10
Classifier: Programming Language :: Python :: 3.11
Classifier: License :: OSI Approved :: MIT License
Classifier: Operating System :: OS Independent
License-File: LICENSE
